README.rst
setup.py
gsutilwrap/__init__.py
gsutilwrap/py.typed
gsutilwrap.egg-info/PKG-INFO
gsutilwrap.egg-info/SOURCES.txt
gsutilwrap.egg-info/dependency_links.txt
gsutilwrap.egg-info/requires.txt
gsutilwrap.egg-info/top_level.txt