Metadata-Version: 1.1
Name: gsutilwrap
Version: 1.1.1
Summary: wraps gsutil, a command-line interface to Google Cloud Storage.
Home-page: https://github.com/Parquery/gsutilwrap
Author: Marko Ristin and Adam Radomski
Author-email: marko@parquery.com
License: UNKNOWN
Keywords: Google cloud storage gcloud gsutil deployment wrap
Platform: UNKNOWN
Classifier: Development Status :: 5 - Production/Stable
Classifier: Intended Audience :: Developers
Classifier: License :: OSI Approved :: MIT License
Classifier: Programming Language :: Python :: 3.5
